design.sv
module voter (I, O);
input [3:0] I; // I 4 men
output [3:1] O; // O Result
reg [3:1] O; 

always@ (I)
   case (I)
   4'b0000:O=3'b100;
   4'b0001:O=3'b100;
   4'b0010:O=3'b100;
   4'b0011:O=3'b010;
   4'b0100:O=3'b100;
   4'b0101:O=3'b010;
   4'b0110:O=3'b010;
   4'b0111:O=3'b001;
   4'b1000:O=3'b100;
   4'b1001:O=3'b010;
   4'b1010:O=3'b010;
   4'b1011:O=3'b001;
   4'b1100:O=3'b010;
   4'b1101:O=3'b001;
   4'b1110:O=3'b001;
   4'b1111:O=3'b001;
   endcase
endmodule

testbench.sv
module voter_tb;
   reg [3:0] I_tb;
   wire [3:1] O_tb;
   voter voter_1(.I(I_tb), .O(O_tb));
initial begin
   #0 I_tb=4'b0000;
   #10 I_tb=4'b0000;
   #10 I_tb=4'b0001;
   #10 I_tb=4'b0010;
   #10 I_tb=4'b0011;
   #10 I_tb=4'b0100;
   #10 I_tb=4'b0101;
   #10 I_tb=4'b0110;
   #10 I_tb=4'b0111;
   #10 I_tb=4'b1000;
   #10 I_tb=4'b1001;
   #10 I_tb=4'b1010;
   #10 I_tb=4'b1011;
   #10 I_tb=4'b1100;
   #10 I_tb=4'b1101;
   #10 I_tb=4'b1110;
   #10 I_tb=4'b1111;
   #10 $finish;
end
initial begin
   $dumpfile("voter.vcd"); 
   $dumpvars(0, voter_1);   
end
endmodule

voter.vcd
$date
	Mon Jun 27 01:48:19 2022
$end
$version
	Icarus Verilog
$end
$timescale
	1s
$end
$scope module voter_tb $end
$scope module voter_1 $end
$var wire 4 ! I [3:0] $end
$var reg 3 " O [3:1] $end
$upscope $end
$upscope $end
$enddefinitions $end
#0
$dumpvars
b100 "
b0 !
$end
#20
b1 !
#30
b10 !
#40
b10 "
b11 !
#50
b100 "
b100 !
#60
b10 "
b101 !
#70
b110 !
#80
b1 "
b111 !
#90
b100 "
b1000 !
#100
b10 "
b1001 !
#110
b1010 !
#120
b1 "
b1011 !
#130
b10 "
b1100 !
#140
b1 "
b1101 !
#150
b1110 !
#160
b1111 !
